{
  "gitSyncId": "696512d08589eb4b1bb0a7c8_dashboard_material_uebersicht",
  "unpublishedPage": {
    "isHidden": false,
    "layouts": [
      {
        "dsl": {
          "backgroundColor": "#F5F5F5",
          "bottomRow": 1200,
          "canExtend": true,
          "containerStyle": "none",
          "detachFromLayout": true,
          "dynamicBindingPathList": [],
          "dynamicTriggerPathList": [],
          "leftColumn": 0,
          "minHeight": 1200,
          "parentColumnSpace": 1,
          "parentRowSpace": 1,
          "rightColumn": 1224,
          "snapColumns": 64,
          "snapRows": 120,
          "topRow": 0,
          "type": "CANVAS_WIDGET",
          "version": 94,
          "widgetId": "0",
          "widgetName": "MainContainer"
        }
      }
    ],
    "name": "MaterialUebersicht",
    "slug": "material-uebersicht"
  }
}
