{
  "gitSyncId": "69679ad93b277e0bf2bd9a2d_2f704afe-4cfe-461a-a7c5-14dbf413acaa",
  "id": "Admin_MaterialData.refresh",
  "pluginId": "js-plugin",
  "pluginType": "JS",
  "unpublishedAction": {
    "actionConfiguration": {
      "encodeParamsToggle": true,
      "jsArguments": [],
      "paginationType": "NONE",
      "timeoutInMillisecond": 10000
    },
    "collectionId": "Admin_MaterialData",
    "confirmBeforeExecute": false,
    "datasource": {
      "isAutoGenerated": false,
      "name": "UNUSED_DATASOURCE",
      "pluginId": "js-plugin"
    },
    "dynamicBindingPathList": [
      {
        "key": "body"
      }
    ],
    "fullyQualifiedName": "MaterialData.refresh",
    "name": "refresh",
    "pageId": "Admin",
    "runBehaviour": "MANUAL",
    "userSetOnLoad": false
  }
}