{
  "gitSyncId": "69679ad93b277e0bf2bd9a2d_ee8964e6-674d-455c-b6e8-db6a5953718f",
  "id": "MaterialUebersicht_HistorieData.myFun1",
  "pluginId": "js-plugin",
  "pluginType": "JS",
  "unpublishedAction": {
    "actionConfiguration": {
      "encodeParamsToggle": true,
      "jsArguments": [],
      "paginationType": "NONE",
      "timeoutInMillisecond": 10000
    },
    "clientSideExecution": true,
    "collectionId": "MaterialUebersicht_HistorieData",
    "confirmBeforeExecute": false,
    "datasource": {
      "isAutoGenerated": false,
      "name": "UNUSED_DATASOURCE",
      "pluginId": "js-plugin"
    },
    "dynamicBindingPathList": [
      {
        "key": "body"
      }
    ],
    "fullyQualifiedName": "HistorieData.myFun1",
    "name": "myFun1",
    "pageId": "MaterialUebersicht",
    "runBehaviour": "MANUAL",
    "userSetOnLoad": false
  }
}