{
  "gitSyncId": "69679ad93b277e0bf2bd9a2d_89222424-b3da-4e19-91e7-ca0c712c9652",
  "id": "Home_MaterialData.getMaterialById",
  "pluginId": "js-plugin",
  "pluginType": "JS",
  "unpublishedAction": {
    "actionConfiguration": {
      "encodeParamsToggle": true,
      "jsArguments": [
        {
          "name": "id"
        }
      ],
      "paginationType": "NONE",
      "timeoutInMillisecond": 10000
    },
    "collectionId": "Home_MaterialData",
    "confirmBeforeExecute": false,
    "datasource": {
      "isAutoGenerated": false,
      "name": "UNUSED_DATASOURCE",
      "pluginId": "js-plugin"
    },
    "dynamicBindingPathList": [
      {
        "key": "body"
      }
    ],
    "fullyQualifiedName": "MaterialData.getMaterialById",
    "name": "getMaterialById",
    "pageId": "Home",
    "runBehaviour": "MANUAL",
    "userSetOnLoad": false
  }
}